mlbodega/__init__.py
mlbodega/ports.py
mlbodega/schemas.py
mlbodega/tinydb/__init__.py
mlbodega/tinydb/experiments.py
mlbodega/tinydb/metrics.py
mlbodega/tinydb/models.py
mlbodega/tinydb/transactions.py
mlbodega-0.1.0.dist-info/LICENSE
mlbodega-0.1.0.dist-info/METADATA
mlbodega-0.1.0.dist-info/WHEEL
mlbodega-0.1.0.dist-info/RECORD
