Metadata-Version: 2.1
Name: mlbodega
Version: 0.1.0
Summary: 
Author: mr-raccoon-97
Author-email: eric.m.cardozo@mi.unc.edu.ar
Requires-Python: >=3.12,<4.0
Classifier: Programming Language :: Python :: 3
Classifier: Programming Language :: Python :: 3.12
Classifier: Programming Language :: Python :: 3.13
Requires-Dist: tinydb (>=4.8.2,<5.0.0)
